matlib/__init__.py
matlib/check.py
matlib/classes.py
matlib/functions.py
matlib-0.1.1.dist-info/LICENSE
matlib-0.1.1.dist-info/METADATA
matlib-0.1.1.dist-info/WHEEL
matlib-0.1.1.dist-info/RECORD
