Metadata-Version: 2.1
Name: matlib
Version: 0.1.1
Summary: 
Author: Denis Demenkov
Author-email: deniska_demenkov@mail.ru
Requires-Python: >=3.10,<4.0
Classifier: Programming Language :: Python :: 3
Classifier: Programming Language :: Python :: 3.10
Classifier: Programming Language :: Python :: 3.11
Requires-Dist: pydantic (>=2.3.0,<3.0.0)
